setup.py
shortn.py
shortn.egg-info/PKG-INFO
shortn.egg-info/SOURCES.txt
shortn.egg-info/dependency_links.txt
shortn.egg-info/entry_points.txt
shortn.egg-info/top_level.txt