Metadata-Version: 1.0
Name: shortn
Version: 0.0.1
Summary: Shorten url using bit.ly, j.mp, t.cn, is.gd, v.gd, tiny.cc.
Home-page: http://github.com/ishu3101/shortn
Author: ishu3101
Author-email: ishu3101@hotmail.com
License: MIT
Keywords: shorten url_shortener shortener short
Platform: UNKNOWN
